[
    {
        "model": "participants.participant",
        "pk": 1,
        "fields": {
            "full_name": "Adam Andriana",
            "isni": "0000000123456789",
            "ipn": "adam@example.com",
            "paypal_email": "adam.paypal@example.com"
        }
    },
    {
        "model": "participants.participant",
        "pk": 2,
        "fields": {
            "full_name": "Bella Brown",
            "isni": "0000000234567890",
            "ipn": "bella@example.com",
            "paypal_email": "bella.paypal@example.com"
        }
    },
    {
        "model": "participants.participant",
        "pk": 3,
        "fields": {
            "full_name": "Charlie Chaplin",
            "isni": "0000000345678901",
            "ipn": "charlie@example.com",
            "paypal_email": "charlie.paypal@example.com"
        }
    },
    {
        "model": "participants.participant",
        "pk": 4,
        "fields": {
            "full_name": "Diana Dors",
            "isni": "0000000456789012",
            "ipn": "diana@example.com",
            "paypal_email": "diana.paypal@example.com"
        }
    },
    {
        "model": "participants.participant",
        "pk": 5,
        "fields": {
            "full_name": "Ethan Edwards",
            "isni": "0000000567890123",
            "ipn": "ethan@example.com",
            "paypal_email": "ethan.paypal@example.com"
        }
    },
    {
        "model": "participants.participant",
        "pk": 6,
        "fields": {
            "full_name": "Fiona Fisher",
            "isni": "0000000678901234",
            "ipn": "fiona@example.com",
            "paypal_email": "fiona.paypal@example.com"
        }
    },
    {
        "model": "participants.participant",
        "pk": 7,
        "fields": {
            "full_name": "George Green",
            "isni": "0000000789012345",
            "ipn": "george@example.com",
            "paypal_email": "george.paypal@example.com"
        }
    },
    {
        "model": "participants.participant",
        "pk": 8,
        "fields": {
            "full_name": "Hannah Hart",
            "isni": "0000000890123456",
            "ipn": "hannah@example.com",
            "paypal_email": "hannah.paypal@example.com"
        }
    },
    {
        "model": "participants.participant",
        "pk": 9,
        "fields": {
            "full_name": "Ian Irving",
            "isni": "0000000901234567",
            "ipn": "ian@example.com",
            "paypal_email": "ian.paypal@example.com"
        }
    },
    {
        "model": "participants.participant",
        "pk": 10,
        "fields": {
            "full_name": "Jane Johnson",
            "isni": "0000001012345678",
            "ipn": "jane@example.com",
            "paypal_email": "jane.paypal@example.com"
        }
    },
    {
        "model": "participants.participant",
        "pk": 11,
        "fields": {
            "full_name": "Kyle King",
            "isni": "0000001123456789",
            "ipn": "kyle@example.com",
            "paypal_email": "kyle.paypal@example.com"
        }
    },
    {
        "model": "participants.participant",
        "pk": 12,
        "fields": {
            "full_name": "Laura Lee",
            "isni": "0000001234567890",
            "ipn": "laura@example.com",
            "paypal_email": "laura.paypal@example.com"
        }
    },
    {
        "model": "participants.participant",
        "pk": 13,
        "fields": {
            "full_name": "Mike Miller",
            "isni": "0000001345678901",
            "ipn": "mike@example.com",
            "paypal_email": "mike.paypal@example.com"
        }
    },
    {
        "model": "participants.participant",
        "pk": 14,
        "fields": {
            "full_name": "Nina North",
            "isni": "0000001456789012",
            "ipn": "nina@example.com",
            "paypal_email": "nina.paypal@example.com"
        }
    },
    {
        "model": "participants.participant",
        "pk": 15,
        "fields": {
            "full_name": "Oscar Owens",
            "isni": "0000001567890123",
            "ipn": "oscar@example.com",
            "paypal_email": "oscar.paypal@example.com"
        }
    }
]